cirrus/CostModel.py
cirrus/GridSearch.py
cirrus/__init__.py
cirrus/cf.py
cirrus/core.py
cirrus/ec2_vm.py
cirrus/graph.py
cirrus/lr.py
cirrus/messenger.py
cirrus/sm.py
cirrus/utils.py
cirrus_ml-0.2.dev0.dist-info/METADATA
cirrus_ml-0.2.dev0.dist-info/RECORD
cirrus_ml-0.2.dev0.dist-info/WHEEL
cirrus_ml-0.2.dev0.dist-info/top_level.txt
