Metadata-Version: 2.1
Name: cirrus-ml
Version: 0.2.dev0
Summary: Python library for Cirrus
Home-page: https://github.com/jcarreira/cirrus
Author: João Carreira
Author-email: joao@berkeley.edu
License: <open file 'LICENSE', mode 'r' at 0x7f911d29f5d0>
Platform: UNKNOWN
